PyRVC.cpython-310-x86_64-linux-gnu.so
libFirmwareUpdate_gcc_v3_1_Basler_pylon.so
libFormatConversion.so
libGCBase_gcc_v3_1_Basler_pylon.so
libGenApi_gcc_v3_1_Basler_pylon.so
libLog_gcc_v3_1_Basler_pylon.so
libMVGigEVisionSDK.so
libMVGigEVisionSDK.so.3.2.0.3
libMVRender.so
libMathParser_gcc_v3_1_Basler_pylon.so
libMediaProcess.so
libMvCameraControl.so
libMvCameraControl.so.3.2.0.3
libMvUsb3vTL.so
libMvUsb3vTL.so.3.2.0.3
libNodeMapData_gcc_v3_1_Basler_pylon.so
libRVC.so
libRVC.so.1
libRVC.so.1.8.3
libXmlParser_gcc_v3_1_Basler_pylon.so
libbxapi-6.2.0.so
libgxapi-6.2.0.so
libgxiapi.so
liblog4cpp_gcc_v3_1_Basler_pylon.so
libpylon_TL_bcon-6.2.0.so
libpylon_TL_camemu-6.2.0.so
libpylon_TL_gige-6.2.0.so
libpylon_TL_gtc-6.2.0.so
libpylon_TL_usb-6.2.0.so
libpylonbase-6.2.0.so
libpylonc-6.2.0.so
libpylonutility-6.2.0.so
libudev.so
libusb-1.0.so
libuxapi-6.2.0.so
pylon-libusb-1.0.so
test_PyRVC3-1.8.3.dist-info/METADATA
test_PyRVC3-1.8.3.dist-info/WHEEL
test_PyRVC3-1.8.3.dist-info/top_level.txt
test_PyRVC3-1.8.3.dist-info/RECORD
