Metadata-Version: 2.1
Name: test-PyRVC3
Version: 1.8.3
Summary: q2
Home-page: UNKNOWN
Author: q2
Author-email: 
License: UNKNOWN
Platform: UNKNOWN
Classifier: Programming Language :: Python :: 3
Classifier: License :: OSI Approved :: MIT License
Requires-Python: >=3
